sensorkit/ascom/__init__.py
sensorkit_ascom-0.1.0.dist-info/METADATA
sensorkit_ascom-0.1.0.dist-info/WHEEL
sensorkit_ascom-0.1.0.dist-info/RECORD
